sapphire_config/__init__.py
sapphire_config/component.py
sapphire_config/metadata.py
sapphire_config/parser.py
sapphire_config-1.0.4.dist-info/LICENSE
sapphire_config-1.0.4.dist-info/METADATA
sapphire_config-1.0.4.dist-info/WHEEL
sapphire_config-1.0.4.dist-info/top_level.txt
sapphire_config-1.0.4.dist-info/RECORD
