Metadata-Version: 2.1
Name: sapphire-config
Version: 1.0.4
Summary: Sapphire Configuration Parser
Author-email: Todd Valentic <todd.valentic@gmail.com>
License: MIT License
Project-URL: Homepage, https://github.com/valentic/sapphire-config
Classifier: Programming Language :: Python :: 3
Classifier: License :: OSI Approved :: MIT License
Classifier: Operating System :: OS Independent
Requires-Python: >=3.9
License-File: LICENSE
Requires-Dist: python-dateutil
Requires-Dist: humanfriendly
Requires-Dist: pytimeparse2
Provides-Extra: devel
Requires-Dist: build ; extra == 'devel'
Requires-Dist: black ; extra == 'devel'
Requires-Dist: pyfakefs ; extra == 'devel'
Requires-Dist: pylint ; extra == 'devel'
Requires-Dist: pytest ; extra == 'devel'
Requires-Dist: ruff ; extra == 'devel'
